LICENSE
README.md
setup.py
bpreg/__init__.py
bpreg.egg-info/PKG-INFO
bpreg.egg-info/SOURCES.txt
bpreg.egg-info/dependency_links.txt
bpreg.egg-info/entry_points.txt
bpreg.egg-info/requires.txt
bpreg.egg-info/top_level.txt
bpreg/dataset/__init__.py
bpreg/dataset/base_dataset.py
bpreg/dataset/bpr_dataset.py
bpreg/dataset/custom_transformations.py
bpreg/dataset/ssbr_dataset.py
bpreg/evaluation/__init__.py
bpreg/evaluation/accuracy.py
bpreg/evaluation/evaluation.py
bpreg/evaluation/landmark_mse.py
bpreg/evaluation/validation_volume.py
bpreg/evaluation/visualization.py
bpreg/inference/__init__.py
bpreg/inference/inference_model.py
bpreg/inference/inference_settings.py
bpreg/network_architecture/__init__.py
bpreg/network_architecture/base_model.py
bpreg/network_architecture/bpr_model.py
bpreg/network_architecture/bpr_model_resnet.py
bpreg/network_architecture/loss_functions.py
bpreg/network_architecture/ssbr_model.py
bpreg/preprocessing/__init__.py
bpreg/preprocessing/dicom2nifti.py
bpreg/preprocessing/nifti2npy.py
bpreg/score_processing/__init__.py
bpreg/score_processing/bodypartexamined_dict.py
bpreg/score_processing/bodypartexamined_tag.py
bpreg/score_processing/landmark_scores.py
bpreg/score_processing/scores.py
bpreg/scripts/__init__.py
bpreg/scripts/bpreg_inference.py
bpreg/scripts/create_config.py
bpreg/scripts/initialize_pretrained_model.py
bpreg/scripts/model_postprocessing.py
bpreg/scripts/train.py
bpreg/settings/__init__.py
bpreg/settings/body-part-metadata.md
bpreg/settings/model_settings.py
bpreg/settings/settings.py
bpreg/utils/__init__.py
bpreg/utils/json_parser.py
bpreg/utils/linear_transformations.py
bpreg/utils/training_utils.py
src/models/README.md
test/test_evaluation.py
test/test_inference.py
test/test_score_processing.py