Metadata-Version: 2.1
Name: bpreg
Version: 1.1.0
Summary: UNKNOWN
Home-page: https://github.com/MIC-DKFZ/BodyPartRegression
Author: Division of Medical Image Computing, German Cancer Research Center
Author-email: mic-office@dkfz.de
Maintainer-email: s.schuhegger@dkfz-heidelberg.de
License: UNKNOWN
Platform: UNKNOWN
